{
  "jobRoles": {
    "Field Sales Executive": {
      "industry": "Sales",
      "description": "Sales and business development roles"
    },
    "In Store Promoter": {
      "industry": "Retail",
      "description": "Retail and promotional activities"
    },
    "Electrician": {
      "industry": "Manufacturing",
      "description": "Electrical installation, maintenance, and repair work"
    },
    "Fitter": {
      "industry": "Manufacturing",
      "description": "Mechanical fitting, assembly, and installation work"
    },
    "Mechanic": {
      "industry": "Manufacturing",
      "description": "Equipment maintenance, repair, and troubleshooting"
    },
    "Machine Operator": {
      "industry": "Manufacturing",
      "description": "Operating and monitoring industrial machinery and equipment"
    },
    "Data Entry Operator": {
      "industry": "Administration",
      "description": "Data entry and administrative work"
    },
    "Tele Salesperson": {
      "industry": "Sales",
      "description": "Telephone-based sales and customer service"
    },
    "Field Sales Person": {
      "industry": "Sales",
      "description": "Field-based sales and business development"
    },
    "ITI (Other)": {
      "industry": "Manufacturing",
      "description": "ITI (Industrial Training Institute) student roles and specializations"
    },
    "Customer Service Executive": {
      "industry": "Customer Service",
      "description": "Customer service and support roles"
    },
    "Call Center Representative": {
      "industry": "Customer Service",
      "description": "Call center and telecommunication support roles"
    },
    "Customer Support Associate": {
      "industry": "Customer Service",
      "description": "Customer support and assistance roles"
    },
    "Service Desk Coordinator": {
      "industry": "Customer Service",
      "description": "Service desk and IT support coordination roles"
    },
    "Technical Support Technician": {
      "industry": "IT Support",
      "description": "Technical support and troubleshooting roles"
    }
  } 
}